linien/VERSION
linien/__init__.py
linien/common.py
linien/config.py
linien/client/__init__.py
linien/client/connection.py
linien/client/exceptions.py
linien/client/remote_parameters.py
linien/client/utils.py
linien_python_client-0.5.3.post2.dist-info/LICENSE
linien_python_client-0.5.3.post2.dist-info/METADATA
linien_python_client-0.5.3.post2.dist-info/WHEEL
linien_python_client-0.5.3.post2.dist-info/top_level.txt
linien_python_client-0.5.3.post2.dist-info/RECORD
